pyplink/__init__.py
pyplink/pyplink.py
pyplink/version.py
pyplink/tests/__init__.py
pyplink/tests/__main__.py
pyplink/tests/test_pyplink.py
pyplink/tests/data/test_data.bed
pyplink/tests/data/test_data.bim
pyplink/tests/data/test_data.fam
pyplink/tests/data/test_data_with_dup.bim
pyplink-1.3.7.dist-info/LICENSE.txt
pyplink-1.3.7.dist-info/METADATA
pyplink-1.3.7.dist-info/WHEEL
pyplink-1.3.7.dist-info/top_level.txt
pyplink-1.3.7.dist-info/RECORD
