Metadata-Version: 2.1
Name: pyplink
Version: 1.3.7
Summary: Python module to read binary Plink files.
Home-page: https://github.com/lemieuxl/pyplink
Author: Louis-Philippe Lemieux Perreault
Author-email: louis-philippe.lemieux.perreault@statgen.org
License: MIT
Keywords: bioinformatics format Plink binary
Classifier: Operating System :: POSIX :: Linux
Classifier: Operating System :: MacOS :: MacOS X
Classifier: Operating System :: Microsoft
Classifier: Programming Language :: Python
Classifier: Programming Language :: Python :: 3
Classifier: Programming Language :: Python :: 3.7
Classifier: Programming Language :: Python :: 3.8
Classifier: Programming Language :: Python :: 3.9
Classifier: Programming Language :: Python :: 3.10
Classifier: Programming Language :: Python :: 3.11
Classifier: Programming Language :: Python :: 3.12
Classifier: License :: OSI Approved :: MIT License
Classifier: Topic :: Scientific/Engineering :: Bio-Informatics
License-File: LICENSE.txt
Requires-Dist: numpy>=1.8.2
Requires-Dist: pandas>=0.17.1
Requires-Dist: six>=1.9.0
